{
    "blendMode": "normal",
    "layerId": "layer_001",
    "name": "線画",
    "opacity": 1.0,
    "strokes": [
        {
            "color": [
                0.7087889909744263,
                0.9034749269485474,
                0.04883650690317154,
                1.0
            ],
            "points": [
                {
                    "pressure": 1.0,
                    "x": 685.9620361328125,
                    "y": 329.7560729980469
                },
                {
                    "pressure": 1.0,
                    "x": 685.9620361328125,
                    "y": 334.09210205078125
                },
                {
                    "pressure": 1.0,
                    "x": 685.9620361328125,
                    "y": 342.7641906738281
                },
                {
                    "pressure": 1.0,
                    "x": 685.9620361328125,
                    "y": 351.436279296875
                },
                {
                    "pressure": 1.0,
                    "x": 685.9620361328125,
                    "y": 360.1083679199219
                },
                {
                    "pressure": 1.0,
                    "x": 681.6259765625,
                    "y": 373.1164855957031
                },
                {
                    "pressure": 1.0,
                    "x": 681.6259765625,
                    "y": 390.4606628417969
                },
                {
                    "pressure": 1.0,
                    "x": 677.2899169921875,
                    "y": 412.1408996582031
                },
                {
                    "pressure": 1.0,
                    "x": 677.2899169921875,
                    "y": 464.17340087890625
                },
                {
                    "pressure": 1.0,
                    "x": 672.953857421875,
                    "y": 477.1815490722656
                },
                {
                    "pressure": 1.0,
                    "x": 672.953857421875,
                    "y": 507.5338439941406
                },
                {
                    "pressure": 1.0,
                    "x": 672.953857421875,
                    "y": 563.9024047851563
                },
                {
                    "pressure": 1.0,
                    "x": 672.953857421875,
                    "y": 615.9349365234375
                },
                {
                    "pressure": 1.0,
                    "x": 672.953857421875,
                    "y": 654.9593505859375
                },
                {
                    "pressure": 1.0,
                    "x": 672.953857421875,
                    "y": 702.6558227539063
                },
                {
                    "pressure": 1.0,
                    "x": 672.953857421875,
                    "y": 741.68017578125
                },
                {
                    "pressure": 1.0,
                    "x": 677.2899169921875,
                    "y": 785.0406494140625
                },
                {
                    "pressure": 1.0,
                    "x": 681.6259765625,
                    "y": 824.0650024414063
                },
                {
                    "pressure": 1.0,
                    "x": 685.9620361328125,
                    "y": 841.4091796875
                },
                {
                    "pressure": 1.0,
                    "x": 690.2980346679688,
                    "y": 876.0975341796875
                },
                {
                    "pressure": 1.0,
                    "x": 698.9701538085938,
                    "y": 915.1219482421875
                },
                {
                    "pressure": 1.0,
                    "x": 703.3062133789063,
                    "y": 949.810302734375
                },
                {
                    "pressure": 1.0,
                    "x": 707.6422119140625,
                    "y": 980.16259765625
                },
                {
                    "pressure": 1.0,
                    "x": 711.978271484375,
                    "y": 1010.514892578125
                },
                {
                    "pressure": 1.0,
                    "x": 716.3143310546875,
                    "y": 1045.2032470703125
                },
                {
                    "pressure": 1.0,
                    "x": 720.650390625,
                    "y": 1066.8834228515625
                },
                {
                    "pressure": 1.0,
                    "x": 724.9863891601563,
                    "y": 1097.2357177734375
                },
                {
                    "pressure": 1.0,
                    "x": 733.6585083007813,
                    "y": 1123.2520751953125
                },
                {
                    "pressure": 1.0,
                    "x": 737.9945068359375,
                    "y": 1136.2601318359375
                },
                {
                    "pressure": 1.0,
                    "x": 742.33056640625,
                    "y": 1149.268310546875
                },
                {
                    "pressure": 1.0,
                    "x": 742.33056640625,
                    "y": 1157.9404296875
                },
                {
                    "pressure": 1.0,
                    "x": 746.6666259765625,
                    "y": 1175.2845458984375
                },
                {
                    "pressure": 1.0,
                    "x": 746.6666259765625,
                    "y": 1192.6287841796875
                },
                {
                    "pressure": 1.0,
                    "x": 755.3386840820313,
                    "y": 1205.6368408203125
                },
                {
                    "pressure": 1.0,
                    "x": 755.3386840820313,
                    "y": 1209.972900390625
                },
                {
                    "pressure": 1.0,
                    "x": 755.3386840820313,
                    "y": 1222.9810791015625
                },
                {
                    "pressure": 1.0,
                    "x": 759.6747436523438,
                    "y": 1235.9891357421875
                },
                {
                    "pressure": 1.0,
                    "x": 759.6747436523438,
                    "y": 1244.6612548828125
                },
                {
                    "pressure": 1.0,
                    "x": 768.3468627929688,
                    "y": 1257.66943359375
                },
                {
                    "pressure": 1.0,
                    "x": 772.682861328125,
                    "y": 1262.00537109375
                },
                {
                    "pressure": 1.0,
                    "x": 777.0189208984375,
                    "y": 1262.00537109375
                },
                {
                    "pressure": 1.0,
                    "x": 781.35498046875,
                    "y": 1266.3414306640625
                },
                {
                    "pressure": 1.0,
                    "x": 794.3630981445313,
                    "y": 1270.677490234375
                },
                {
                    "pressure": 1.0,
                    "x": 803.0352172851563,
                    "y": 1270.677490234375
                },
                {
                    "pressure": 1.0,
                    "x": 820.37939453125,
                    "y": 1279.349609375
                },
                {
                    "pressure": 1.0,
                    "x": 846.3956298828125,
                    "y": 1279.349609375
                },
                {
                    "pressure": 1.0,
                    "x": 855.0676879882813,
                    "y": 1279.349609375
                },
                {
                    "pressure": 1.0,
                    "x": 876.7479248046875,
                    "y": 1279.349609375
                },
                {
                    "pressure": 1.0,
                    "x": 898.4281616210938,
                    "y": 1283.6856689453125
                },
                {
                    "pressure": 1.0,
                    "x": 911.436279296875,
                    "y": 1283.6856689453125
                },
                {
                    "pressure": 1.0,
                    "x": 941.78857421875,
                    "y": 1288.021728515625
                },
                {
                    "pressure": 1.0,
                    "x": 963.4688110351563,
                    "y": 1288.021728515625
                },
                {
                    "pressure": 1.0,
                    "x": 985.1490478515625,
                    "y": 1288.021728515625
                },
                {
                    "pressure": 1.0,
                    "x": 993.8211059570313,
                    "y": 1288.021728515625
                },
                {
                    "pressure": 1.0,
                    "x": 1011.165283203125,
                    "y": 1288.021728515625
                },
                {
                    "pressure": 1.0,
                    "x": 1019.8373413085938,
                    "y": 1288.021728515625
                },
                {
                    "pressure": 1.0,
                    "x": 1024.1734619140625,
                    "y": 1288.021728515625
                },
                {
                    "pressure": 1.0,
                    "x": 1032.845458984375,
                    "y": 1288.021728515625
                },
                {
                    "pressure": 1.0,
                    "x": 1037.1815185546875,
                    "y": 1288.021728515625
                },
                {
                    "pressure": 1.0,
                    "x": 1037.1815185546875,
                    "y": 1283.6856689453125
                },
                {
                    "pressure": 1.0,
                    "x": 1037.1815185546875,
                    "y": 1275.0135498046875
                },
                {
                    "pressure": 1.0,
                    "x": 1041.517578125,
                    "y": 1270.677490234375
                },
                {
                    "pressure": 1.0,
                    "x": 1041.517578125,
                    "y": 1257.66943359375
                },
                {
                    "pressure": 1.0,
                    "x": 1041.517578125,
                    "y": 1253.3333740234375
                },
                {
                    "pressure": 1.0,
                    "x": 1041.517578125,
                    "y": 1240.3251953125
                },
                {
                    "pressure": 1.0,
                    "x": 1041.517578125,
                    "y": 1231.653076171875
                },
                {
                    "pressure": 1.0,
                    "x": 1041.517578125,
                    "y": 1209.972900390625
                },
                {
                    "pressure": 1.0,
                    "x": 1041.517578125,
                    "y": 1196.9647216796875
                },
                {
                    "pressure": 1.0,
                    "x": 1041.517578125,
                    "y": 1170.948486328125
                },
                {
                    "pressure": 1.0,
                    "x": 1041.517578125,
                    "y": 1136.2601318359375
                },
                {
                    "pressure": 1.0,
                    "x": 1041.517578125,
                    "y": 1123.2520751953125
                },
                {
                    "pressure": 1.0,
                    "x": 1037.1815185546875,
                    "y": 1092.8997802734375
                },
                {
                    "pressure": 1.0,
                    "x": 1037.1815185546875,
                    "y": 1079.8916015625
                },
                {
                    "pressure": 1.0,
                    "x": 1037.1815185546875,
                    "y": 1049.539306640625
                },
                {
                    "pressure": 1.0,
                    "x": 1032.845458984375,
                    "y": 1040.8671875
                },
                {
                    "pressure": 1.0,
                    "x": 1028.5093994140625,
                    "y": 1010.514892578125
                },
                {
                    "pressure": 1.0,
                    "x": 1024.1734619140625,
                    "y": 993.1707153320313
                },
                {
                    "pressure": 1.0,
                    "x": 1024.1734619140625,
                    "y": 958.4823608398438
                },
                {
                    "pressure": 1.0,
                    "x": 1019.8373413085938,
                    "y": 945.4742431640625
                },
                {
                    "pressure": 1.0,
                    "x": 1019.8373413085938,
                    "y": 906.4498291015625
                },
                {
                    "pressure": 1.0,
                    "x": 1019.8373413085938,
                    "y": 867.4254760742188
                },
                {
                    "pressure": 1.0,
                    "x": 1019.8373413085938,
                    "y": 854.4173583984375
                },
                {
                    "pressure": 1.0,
                    "x": 1019.8373413085938,
                    "y": 828.4010620117188
                },
                {
                    "pressure": 1.0,
                    "x": 1019.8373413085938,
                    "y": 815.3929443359375
                },
                {
                    "pressure": 1.0,
                    "x": 1019.8373413085938,
                    "y": 793.7127075195313
                },
                {
                    "pressure": 1.0,
                    "x": 1019.8373413085938,
                    "y": 780.70458984375
                },
                {
                    "pressure": 1.0,
                    "x": 1019.8373413085938,
                    "y": 750.352294921875
                },
                {
                    "pressure": 1.0,
                    "x": 1019.8373413085938,
                    "y": 715.6639404296875
                },
                {
                    "pressure": 1.0,
                    "x": 1019.8373413085938,
                    "y": 706.9918212890625
                },
                {
                    "pressure": 1.0,
                    "x": 1019.8373413085938,
                    "y": 680.9755859375
                },
                {
                    "pressure": 1.0,
                    "x": 1019.8373413085938,
                    "y": 672.3035278320313
                },
                {
                    "pressure": 1.0,
                    "x": 1019.8373413085938,
                    "y": 654.9593505859375
                },
                {
                    "pressure": 1.0,
                    "x": 1019.8373413085938,
                    "y": 646.2872314453125
                },
                {
                    "pressure": 1.0,
                    "x": 1019.8373413085938,
                    "y": 624.6069946289063
                },
                {
                    "pressure": 1.0,
                    "x": 1019.8373413085938,
                    "y": 602.9268188476563
                },
                {
                    "pressure": 1.0,
                    "x": 1019.8373413085938,
                    "y": 598.5907592773438
                },
                {
                    "pressure": 1.0,
                    "x": 1019.8373413085938,
                    "y": 585.5826416015625
                },
                {
                    "pressure": 1.0,
                    "x": 1019.8373413085938,
                    "y": 576.9105224609375
                },
                {
                    "pressure": 1.0,
                    "x": 1024.1734619140625,
                    "y": 568.2384643554688
                },
                {
                    "pressure": 1.0,
                    "x": 1024.1734619140625,
                    "y": 563.9024047851563
                },
                {
                    "pressure": 1.0,
                    "x": 1024.1734619140625,
                    "y": 546.5582275390625
                },
                {
                    "pressure": 1.0,
                    "x": 1024.1734619140625,
                    "y": 537.8861694335938
                },
                {
                    "pressure": 1.0,
                    "x": 1024.1734619140625,
                    "y": 524.8780517578125
                },
                {
                    "pressure": 1.0,
                    "x": 1024.1734619140625,
                    "y": 516.2059326171875
                },
                {
                    "pressure": 1.0,
                    "x": 1024.1734619140625,
                    "y": 503.19781494140625
                },
                {
                    "pressure": 1.0,
                    "x": 1024.1734619140625,
                    "y": 490.1896667480469
                },
                {
                    "pressure": 1.0,
                    "x": 1024.1734619140625,
                    "y": 485.8536376953125
                },
                {
                    "pressure": 1.0,
                    "x": 1024.1734619140625,
                    "y": 472.8454895019531
                },
                {
                    "pressure": 1.0,
                    "x": 1024.1734619140625,
                    "y": 468.50946044921875
                },
                {
                    "pressure": 1.0,
                    "x": 1024.1734619140625,
                    "y": 451.165283203125
                },
                {
                    "pressure": 1.0,
                    "x": 1019.8373413085938,
                    "y": 442.4931945800781
                },
                {
                    "pressure": 1.0,
                    "x": 1019.8373413085938,
                    "y": 429.4850769042969
                },
                {
                    "pressure": 1.0,
                    "x": 1019.8373413085938,
                    "y": 420.81298828125
                },
                {
                    "pressure": 1.0,
                    "x": 1019.8373413085938,
                    "y": 416.4769287109375
                },
                {
                    "pressure": 1.0,
                    "x": 1019.8373413085938,
                    "y": 412.1408996582031
                },
                {
                    "pressure": 1.0,
                    "x": 1015.5013427734375,
                    "y": 403.46881103515625
                },
                {
                    "pressure": 1.0,
                    "x": 1015.5013427734375,
                    "y": 399.13275146484375
                },
                {
                    "pressure": 1.0,
                    "x": 1011.165283203125,
                    "y": 394.7967224121094
                },
                {
                    "pressure": 1.0,
                    "x": 1006.8292236328125,
                    "y": 386.1246337890625
                },
                {
                    "pressure": 1.0,
                    "x": 1006.8292236328125,
                    "y": 381.78857421875
                },
                {
                    "pressure": 1.0,
                    "x": 1002.4932250976563,
                    "y": 381.78857421875
                },
                {
                    "pressure": 1.0,
                    "x": 1002.4932250976563,
                    "y": 377.4525451660156
                },
                {
                    "pressure": 1.0,
                    "x": 993.8211059570313,
                    "y": 373.1164855957031
                },
                {
                    "pressure": 1.0,
                    "x": 993.8211059570313,
                    "y": 368.78045654296875
                },
                {
                    "pressure": 1.0,
                    "x": 989.4850463867188,
                    "y": 368.78045654296875
                },
                {
                    "pressure": 1.0,
                    "x": 985.1490478515625,
                    "y": 368.78045654296875
                },
                {
                    "pressure": 1.0,
                    "x": 980.81298828125,
                    "y": 368.78045654296875
                },
                {
                    "pressure": 1.0,
                    "x": 976.4769287109375,
                    "y": 368.78045654296875
                },
                {
                    "pressure": 1.0,
                    "x": 972.140869140625,
                    "y": 368.78045654296875
                },
                {
                    "pressure": 1.0,
                    "x": 963.4688110351563,
                    "y": 368.78045654296875
                },
                {
                    "pressure": 1.0,
                    "x": 959.1327514648438,
                    "y": 368.78045654296875
                },
                {
                    "pressure": 1.0,
                    "x": 946.1246337890625,
                    "y": 368.78045654296875
                },
                {
                    "pressure": 1.0,
                    "x": 941.78857421875,
                    "y": 368.78045654296875
                },
                {
                    "pressure": 1.0,
                    "x": 933.1165161132813,
                    "y": 368.78045654296875
                },
                {
                    "pressure": 1.0,
                    "x": 928.7804565429688,
                    "y": 368.78045654296875
                },
                {
                    "pressure": 1.0,
                    "x": 920.1083374023438,
                    "y": 368.78045654296875
                },
                {
                    "pressure": 1.0,
                    "x": 911.436279296875,
                    "y": 364.44439697265625
                },
                {
                    "pressure": 1.0,
                    "x": 898.4281616210938,
                    "y": 360.1083679199219
                },
                {
                    "pressure": 1.0,
                    "x": 855.0676879882813,
                    "y": 355.7723083496094
                },
                {
                    "pressure": 1.0,
                    "x": 842.0595703125,
                    "y": 351.436279296875
                },
                {
                    "pressure": 1.0,
                    "x": 820.37939453125,
                    "y": 347.1002502441406
                },
                {
                    "pressure": 1.0,
                    "x": 807.3712158203125,
                    "y": 347.1002502441406
                },
                {
                    "pressure": 1.0,
                    "x": 794.3630981445313,
                    "y": 347.1002502441406
                },
                {
                    "pressure": 1.0,
                    "x": 777.0189208984375,
                    "y": 347.1002502441406
                },
                {
                    "pressure": 1.0,
                    "x": 772.682861328125,
                    "y": 347.1002502441406
                },
                {
                    "pressure": 1.0,
                    "x": 768.3468627929688,
                    "y": 347.1002502441406
                },
                {
                    "pressure": 1.0,
                    "x": 764.0108032226563,
                    "y": 342.7641906738281
                },
                {
                    "pressure": 1.0,
                    "x": 759.6747436523438,
                    "y": 342.7641906738281
                },
                {
                    "pressure": 1.0,
                    "x": 759.6747436523438,
                    "y": 338.42816162109375
                }
            ],
            "radiusPx": 4.0
        },
        {
            "color": [
                0.7087889909744263,
                0.9034749269485474,
                0.04883650690317154,
                1.0
            ],
            "points": [
                {
                    "pressure": 1.0,
                    "x": 1496.8021240234375,
                    "y": 316.7479248046875
                },
                {
                    "pressure": 1.0,
                    "x": 1496.8021240234375,
                    "y": 325.4200134277344
                },
                {
                    "pressure": 1.0,
                    "x": 1488.130126953125,
                    "y": 334.09210205078125
                },
                {
                    "pressure": 1.0,
                    "x": 1483.7940673828125,
                    "y": 338.42816162109375
                },
                {
                    "pressure": 1.0,
                    "x": 1475.1219482421875,
                    "y": 342.7641906738281
                },
                {
                    "pressure": 1.0,
                    "x": 1453.4417724609375,
                    "y": 360.1083679199219
                },
                {
                    "pressure": 1.0,
                    "x": 1449.105712890625,
                    "y": 364.44439697265625
                },
                {
                    "pressure": 1.0,
                    "x": 1440.43359375,
                    "y": 368.78045654296875
                },
                {
                    "pressure": 1.0,
                    "x": 1427.4254150390625,
                    "y": 381.78857421875
                },
                {
                    "pressure": 1.0,
                    "x": 1418.75341796875,
                    "y": 386.1246337890625
                },
                {
                    "pressure": 1.0,
                    "x": 1414.4173583984375,
                    "y": 394.7967224121094
                },
                {
                    "pressure": 1.0,
                    "x": 1405.7452392578125,
                    "y": 399.13275146484375
                },
                {
                    "pressure": 1.0,
                    "x": 1397.0731201171875,
                    "y": 412.1408996582031
                },
                {
                    "pressure": 1.0,
                    "x": 1392.737060546875,
                    "y": 420.81298828125
                },
                {
                    "pressure": 1.0,
                    "x": 1388.401123046875,
                    "y": 425.1490173339844
                },
                {
                    "pressure": 1.0,
                    "x": 1388.401123046875,
                    "y": 433.82110595703125
                },
                {
                    "pressure": 1.0,
                    "x": 1384.0650634765625,
                    "y": 464.17340087890625
                },
                {
                    "pressure": 1.0,
                    "x": 1379.72900390625,
                    "y": 472.8454895019531
                },
                {
                    "pressure": 1.0,
                    "x": 1379.72900390625,
                    "y": 481.517578125
                },
                {
                    "pressure": 1.0,
                    "x": 1379.72900390625,
                    "y": 494.5257263183594
                },
                {
                    "pressure": 1.0,
                    "x": 1375.3929443359375,
                    "y": 520.5419921875
                },
                {
                    "pressure": 1.0,
                    "x": 1375.3929443359375,
                    "y": 529.2140502929688
                },
                {
                    "pressure": 1.0,
                    "x": 1375.3929443359375,
                    "y": 537.8861694335938
                },
                {
                    "pressure": 1.0,
                    "x": 1375.3929443359375,
                    "y": 550.894287109375
                },
                {
                    "pressure": 1.0,
                    "x": 1375.3929443359375,
                    "y": 576.9105224609375
                },
                {
                    "pressure": 1.0,
                    "x": 1375.3929443359375,
                    "y": 589.918701171875
                },
                {
                    "pressure": 1.0,
                    "x": 1384.0650634765625,
                    "y": 602.9268188476563
                },
                {
                    "pressure": 1.0,
                    "x": 1392.737060546875,
                    "y": 641.951171875
                },
                {
                    "pressure": 1.0,
                    "x": 1401.4091796875,
                    "y": 663.6314086914063
                },
                {
                    "pressure": 1.0,
                    "x": 1401.4091796875,
                    "y": 676.6395263671875
                },
                {
                    "pressure": 1.0,
                    "x": 1410.081298828125,
                    "y": 689.647705078125
                },
                {
                    "pressure": 1.0,
                    "x": 1418.75341796875,
                    "y": 733.0081176757813
                },
                {
                    "pressure": 1.0,
                    "x": 1423.0894775390625,
                    "y": 746.0162353515625
                },
                {
                    "pressure": 1.0,
                    "x": 1423.0894775390625,
                    "y": 759.0243530273438
                },
                {
                    "pressure": 1.0,
                    "x": 1427.4254150390625,
                    "y": 776.3685302734375
                },
                {
                    "pressure": 1.0,
                    "x": 1436.0975341796875,
                    "y": 824.0650024414063
                },
                {
                    "pressure": 1.0,
                    "x": 1440.43359375,
                    "y": 837.0731811523438
                },
                {
                    "pressure": 1.0,
                    "x": 1444.7696533203125,
                    "y": 858.7533569335938
                },
                {
                    "pressure": 1.0,
                    "x": 1453.4417724609375,
                    "y": 876.0975341796875
                },
                {
                    "pressure": 1.0,
                    "x": 1479.4580078125,
                    "y": 919.4580078125
                },
                {
                    "pressure": 1.0,
                    "x": 1483.7940673828125,
                    "y": 928.1300659179688
                },
                {
                    "pressure": 1.0,
                    "x": 1492.466064453125,
                    "y": 936.8021850585938
                },
                {
                    "pressure": 1.0,
                    "x": 1496.8021240234375,
                    "y": 954.1463623046875
                },
                {
                    "pressure": 1.0,
                    "x": 1514.1463623046875,
                    "y": 980.16259765625
                },
                {
                    "pressure": 1.0,
                    "x": 1527.1544189453125,
                    "y": 993.1707153320313
                },
                {
                    "pressure": 1.0,
                    "x": 1535.8265380859375,
                    "y": 1010.514892578125
                },
                {
                    "pressure": 1.0,
                    "x": 1570.514892578125,
                    "y": 1040.8671875
                },
                {
                    "pressure": 1.0,
                    "x": 1583.5230712890625,
                    "y": 1053.8753662109375
                },
                {
                    "pressure": 1.0,
                    "x": 1600.8671875,
                    "y": 1058.21142578125
                },
                {
                    "pressure": 1.0,
                    "x": 1613.8753662109375,
                    "y": 1066.8834228515625
                },
                {
                    "pressure": 1.0,
                    "x": 1644.2276611328125,
                    "y": 1075.5555419921875
                },
                {
                    "pressure": 1.0,
                    "x": 1657.2357177734375,
                    "y": 1079.8916015625
                },
                {
                    "pressure": 1.0,
                    "x": 1670.243896484375,
                    "y": 1084.2276611328125
                },
                {
                    "pressure": 1.0,
                    "x": 1726.6124267578125,
                    "y": 1097.2357177734375
                },
                {
                    "pressure": 1.0,
                    "x": 1743.9566650390625,
                    "y": 1097.2357177734375
                },
                {
                    "pressure": 1.0,
                    "x": 1765.6368408203125,
                    "y": 1097.2357177734375
                },
                {
                    "pressure": 1.0,
                    "x": 1817.66943359375,
                    "y": 1101.57177734375
                },
                {
                    "pressure": 1.0,
                    "x": 1843.6856689453125,
                    "y": 1101.57177734375
                },
                {
                    "pressure": 1.0,
                    "x": 1887.046142578125,
                    "y": 1101.57177734375
                },
                {
                    "pressure": 1.0,
                    "x": 1926.0704345703125,
                    "y": 1101.57177734375
                },
                {
                    "pressure": 1.0,
                    "x": 1969.430908203125,
                    "y": 1101.57177734375
                },
                {
                    "pressure": 1.0,
                    "x": 1982.4390869140625,
                    "y": 1101.57177734375
                },
                {
                    "pressure": 1.0,
                    "x": 2012.7913818359375,
                    "y": 1101.57177734375
                },
                {
                    "pressure": 1.0,
                    "x": 2043.1436767578125,
                    "y": 1097.2357177734375
                },
                {
                    "pressure": 1.0,
                    "x": 2060.48779296875,
                    "y": 1097.2357177734375
                },
                {
                    "pressure": 1.0,
                    "x": 2073.495849609375,
                    "y": 1092.8997802734375
                },
                {
                    "pressure": 1.0,
                    "x": 2077.83203125,
                    "y": 1088.563720703125
                },
                {
                    "pressure": 1.0,
                    "x": 2086.504150390625,
                    "y": 1088.563720703125
                },
                {
                    "pressure": 1.0,
                    "x": 2090.840087890625,
                    "y": 1092.8997802734375
                },
                {
                    "pressure": 1.0,
                    "x": 2090.840087890625,
                    "y": 1101.57177734375
                },
                {
                    "pressure": 1.0,
                    "x": 2090.840087890625,
                    "y": 1123.2520751953125
                },
                {
                    "pressure": 1.0,
                    "x": 2090.840087890625,
                    "y": 1140.59619140625
                },
                {
                    "pressure": 1.0,
                    "x": 2090.840087890625,
                    "y": 1153.6043701171875
                },
                {
                    "pressure": 1.0,
                    "x": 2090.840087890625,
                    "y": 1170.948486328125
                },
                {
                    "pressure": 1.0,
                    "x": 2090.840087890625,
                    "y": 1214.3089599609375
                },
                {
                    "pressure": 1.0,
                    "x": 2090.840087890625,
                    "y": 1231.653076171875
                },
                {
                    "pressure": 1.0,
                    "x": 2095.17626953125,
                    "y": 1248.997314453125
                },
                {
                    "pressure": 1.0,
                    "x": 2103.84814453125,
                    "y": 1283.6856689453125
                },
                {
                    "pressure": 1.0,
                    "x": 2108.184326171875,
                    "y": 1296.6937255859375
                },
                {
                    "pressure": 1.0,
                    "x": 2112.520263671875,
                    "y": 1305.3658447265625
                },
                {
                    "pressure": 1.0,
                    "x": 2116.8564453125,
                    "y": 1314.0379638671875
                },
                {
                    "pressure": 1.0,
                    "x": 2125.528564453125,
                    "y": 1331.382080078125
                },
                {
                    "pressure": 1.0,
                    "x": 2129.864501953125,
                    "y": 1335.7181396484375
                },
                {
                    "pressure": 1.0,
                    "x": 2129.864501953125,
                    "y": 1340.05419921875
                },
                {
                    "pressure": 1.0,
                    "x": 2134.20068359375,
                    "y": 1340.05419921875
                },
                {
                    "pressure": 1.0,
                    "x": 2142.87255859375,
                    "y": 1348.726318359375
                },
                {
                    "pressure": 1.0,
                    "x": 2147.208740234375,
                    "y": 1353.0623779296875
                },
                {
                    "pressure": 1.0,
                    "x": 2155.880859375,
                    "y": 1366.0704345703125
                },
                {
                    "pressure": 1.0,
                    "x": 2173.224853515625,
                    "y": 1387.750732421875
                },
                {
                    "pressure": 1.0,
                    "x": 2181.89697265625,
                    "y": 1392.0867919921875
                },
                {
                    "pressure": 1.0,
                    "x": 2186.233154296875,
                    "y": 1396.4227294921875
                },
                {
                    "pressure": 1.0,
                    "x": 2190.569091796875,
                    "y": 1396.4227294921875
                },
                {
                    "pressure": 1.0,
                    "x": 2194.9052734375,
                    "y": 1396.4227294921875
                },
                {
                    "pressure": 1.0,
                    "x": 2203.5771484375,
                    "y": 1392.0867919921875
                },
                {
                    "pressure": 1.0,
                    "x": 2203.5771484375,
                    "y": 1387.750732421875
                },
                {
                    "pressure": 1.0,
                    "x": 2212.249267578125,
                    "y": 1383.4146728515625
                },
                {
                    "pressure": 1.0,
                    "x": 2212.249267578125,
                    "y": 1379.07861328125
                },
                {
                    "pressure": 1.0,
                    "x": 2225.25732421875,
                    "y": 1370.406494140625
                },
                {
                    "pressure": 1.0,
                    "x": 2233.929443359375,
                    "y": 1366.0704345703125
                },
                {
                    "pressure": 1.0,
                    "x": 2242.6015625,
                    "y": 1357.3984375
                },
                {
                    "pressure": 1.0,
                    "x": 2246.9375,
                    "y": 1353.0623779296875
                },
                {
                    "pressure": 1.0,
                    "x": 2268.61767578125,
                    "y": 1331.382080078125
                },
                {
                    "pressure": 1.0,
                    "x": 2272.953857421875,
                    "y": 1318.3740234375
                },
                {
                    "pressure": 1.0,
                    "x": 2277.289794921875,
                    "y": 1305.3658447265625
                },
                {
                    "pressure": 1.0,
                    "x": 2294.634033203125,
                    "y": 1262.00537109375
                },
                {
                    "pressure": 1.0,
                    "x": 2294.634033203125,
                    "y": 1244.6612548828125
                },
                {
                    "pressure": 1.0,
                    "x": 2298.969970703125,
                    "y": 1227.317138671875
                },
                {
                    "pressure": 1.0,
                    "x": 2298.969970703125,
                    "y": 1214.3089599609375
                },
                {
                    "pressure": 1.0,
                    "x": 2290.298095703125,
                    "y": 1175.2845458984375
                },
                {
                    "pressure": 1.0,
                    "x": 2285.9619140625,
                    "y": 1162.2763671875
                },
                {
                    "pressure": 1.0,
                    "x": 2272.953857421875,
                    "y": 1144.9322509765625
                },
                {
                    "pressure": 1.0,
                    "x": 2264.28173828125,
                    "y": 1131.924072265625
                },
                {
                    "pressure": 1.0,
                    "x": 2233.929443359375,
                    "y": 1110.243896484375
                },
                {
                    "pressure": 1.0,
                    "x": 2220.92138671875,
                    "y": 1097.2357177734375
                },
                {
                    "pressure": 1.0,
                    "x": 2212.249267578125,
                    "y": 1092.8997802734375
                },
                {
                    "pressure": 1.0,
                    "x": 2190.569091796875,
                    "y": 1079.8916015625
                },
                {
                    "pressure": 1.0,
                    "x": 2151.544677734375,
                    "y": 1053.8753662109375
                },
                {
                    "pressure": 1.0,
                    "x": 2134.20068359375,
                    "y": 1045.2032470703125
                },
                {
                    "pressure": 1.0,
                    "x": 2129.864501953125,
                    "y": 1040.8671875
                },
                {
                    "pressure": 1.0,
                    "x": 2121.1923828125,
                    "y": 1040.8671875
                },
                {
                    "pressure": 1.0,
                    "x": 2121.1923828125,
                    "y": 1036.5311279296875
                },
                {
                    "pressure": 1.0,
                    "x": 2116.8564453125,
                    "y": 1036.5311279296875
                },
                {
                    "pressure": 1.0,
                    "x": 2116.8564453125,
                    "y": 1032.195068359375
                },
                {
                    "pressure": 1.0,
                    "x": 2116.8564453125,
                    "y": 1027.859130859375
                },
                {
                    "pressure": 1.0,
                    "x": 2121.1923828125,
                    "y": 1023.5230102539063
                },
                {
                    "pressure": 1.0,
                    "x": 2134.20068359375,
                    "y": 1019.18701171875
                },
                {
                    "pressure": 1.0,
                    "x": 2142.87255859375,
                    "y": 1014.8509521484375
                },
                {
                    "pressure": 1.0,
                    "x": 2155.880859375,
                    "y": 1010.514892578125
                },
                {
                    "pressure": 1.0,
                    "x": 2173.224853515625,
                    "y": 1006.1788330078125
                },
                {
                    "pressure": 1.0,
                    "x": 2194.9052734375,
                    "y": 1001.8428344726563
                },
                {
                    "pressure": 1.0,
                    "x": 2212.249267578125,
                    "y": 1001.8428344726563
                },
                {
                    "pressure": 1.0,
                    "x": 2264.28173828125,
                    "y": 984.4986572265625
                },
                {
                    "pressure": 1.0,
                    "x": 2281.6259765625,
                    "y": 980.16259765625
                },
                {
                    "pressure": 1.0,
                    "x": 2303.30615234375,
                    "y": 975.8265380859375
                },
                {
                    "pressure": 1.0,
                    "x": 2316.314208984375,
                    "y": 971.4905395507813
                },
                {
                    "pressure": 1.0,
                    "x": 2351.002685546875,
                    "y": 958.4823608398438
                },
                {
                    "pressure": 1.0,
                    "x": 2359.6748046875,
                    "y": 954.1463623046875
                },
                {
                    "pressure": 1.0,
                    "x": 2364.0107421875,
                    "y": 949.810302734375
                },
                {
                    "pressure": 1.0,
                    "x": 2372.682861328125,
                    "y": 941.13818359375
                },
                {
                    "pressure": 1.0,
                    "x": 2372.682861328125,
                    "y": 936.8021850585938
                },
                {
                    "pressure": 1.0,
                    "x": 2372.682861328125,
                    "y": 928.1300659179688
                },
                {
                    "pressure": 1.0,
                    "x": 2372.682861328125,
                    "y": 923.7940063476563
                },
                {
                    "pressure": 1.0,
                    "x": 2372.682861328125,
                    "y": 919.4580078125
                },
                {
                    "pressure": 1.0,
                    "x": 2372.682861328125,
                    "y": 906.4498291015625
                },
                {
                    "pressure": 1.0,
                    "x": 2364.0107421875,
                    "y": 897.7777709960938
                },
                {
                    "pressure": 1.0,
                    "x": 2359.6748046875,
                    "y": 889.1056518554688
                },
                {
                    "pressure": 1.0,
                    "x": 2342.33056640625,
                    "y": 867.4254760742188
                },
                {
                    "pressure": 1.0,
                    "x": 2337.994384765625,
                    "y": 854.4173583984375
                },
                {
                    "pressure": 1.0,
                    "x": 2324.986328125,
                    "y": 845.7452392578125
                },
                {
                    "pressure": 1.0,
                    "x": 2316.314208984375,
                    "y": 837.0731811523438
                },
                {
                    "pressure": 1.0,
                    "x": 2316.314208984375,
                    "y": 832.7371215820313
                },
                {
                    "pressure": 1.0,
                    "x": 2311.978271484375,
                    "y": 832.7371215820313
                },
                {
                    "pressure": 1.0,
                    "x": 2307.64208984375,
                    "y": 832.7371215820313
                },
                {
                    "pressure": 1.0,
                    "x": 2303.30615234375,
                    "y": 832.7371215820313
                },
                {
                    "pressure": 1.0,
                    "x": 2294.634033203125,
                    "y": 832.7371215820313
                },
                {
                    "pressure": 1.0,
                    "x": 2285.9619140625,
                    "y": 832.7371215820313
                },
                {
                    "pressure": 1.0,
                    "x": 2277.289794921875,
                    "y": 832.7371215820313
                },
                {
                    "pressure": 1.0,
                    "x": 2251.273681640625,
                    "y": 841.4091796875
                },
                {
                    "pressure": 1.0,
                    "x": 2238.265380859375,
                    "y": 845.7452392578125
                },
                {
                    "pressure": 1.0,
                    "x": 2220.92138671875,
                    "y": 845.7452392578125
                },
                {
                    "pressure": 1.0,
                    "x": 2212.249267578125,
                    "y": 850.081298828125
                },
                {
                    "pressure": 1.0,
                    "x": 2186.233154296875,
                    "y": 863.0894165039063
                },
                {
                    "pressure": 1.0,
                    "x": 2173.224853515625,
                    "y": 863.0894165039063
                },
                {
                    "pressure": 1.0,
                    "x": 2164.552978515625,
                    "y": 867.4254760742188
                },
                {
                    "pressure": 1.0,
                    "x": 2151.544677734375,
                    "y": 867.4254760742188
                },
                {
                    "pressure": 1.0,
                    "x": 2129.864501953125,
                    "y": 876.0975341796875
                },
                {
                    "pressure": 1.0,
                    "x": 2121.1923828125,
                    "y": 876.0975341796875
                },
                {
                    "pressure": 1.0,
                    "x": 2112.520263671875,
                    "y": 876.0975341796875
                },
                {
                    "pressure": 1.0,
                    "x": 2099.51220703125,
                    "y": 876.0975341796875
                },
                {
                    "pressure": 1.0,
                    "x": 2077.83203125,
                    "y": 880.43359375
                },
                {
                    "pressure": 1.0,
                    "x": 2064.823974609375,
                    "y": 880.43359375
                },
                {
                    "pressure": 1.0,
                    "x": 2060.48779296875,
                    "y": 880.43359375
                },
                {
                    "pressure": 1.0,
                    "x": 2047.479736328125,
                    "y": 880.43359375
                },
                {
                    "pressure": 1.0,
                    "x": 2043.1436767578125,
                    "y": 884.7696533203125
                },
                {
                    "pressure": 1.0,
                    "x": 2034.4715576171875,
                    "y": 884.7696533203125
                },
                {
                    "pressure": 1.0,
                    "x": 2030.135498046875,
                    "y": 884.7696533203125
                },
                {
                    "pressure": 1.0,
                    "x": 2025.7994384765625,
                    "y": 884.7696533203125
                },
                {
                    "pressure": 1.0,
                    "x": 2025.7994384765625,
                    "y": 880.43359375
                },
                {
                    "pressure": 1.0,
                    "x": 2025.7994384765625,
                    "y": 876.0975341796875
                },
                {
                    "pressure": 1.0,
                    "x": 2025.7994384765625,
                    "y": 867.4254760742188
                },
                {
                    "pressure": 1.0,
                    "x": 2021.46337890625,
                    "y": 850.081298828125
                },
                {
                    "pressure": 1.0,
                    "x": 2021.46337890625,
                    "y": 837.0731811523438
                },
                {
                    "pressure": 1.0,
                    "x": 2021.46337890625,
                    "y": 815.3929443359375
                },
                {
                    "pressure": 1.0,
                    "x": 2025.7994384765625,
                    "y": 789.376708984375
                },
                {
                    "pressure": 1.0,
                    "x": 2034.4715576171875,
                    "y": 763.3604125976563
                },
                {
                    "pressure": 1.0,
                    "x": 2043.1436767578125,
                    "y": 733.0081176757813
                },
                {
                    "pressure": 1.0,
                    "x": 2056.15185546875,
                    "y": 685.3116455078125
                },
                {
                    "pressure": 1.0,
                    "x": 2069.159912109375,
                    "y": 663.6314086914063
                },
                {
                    "pressure": 1.0,
                    "x": 2077.83203125,
                    "y": 641.951171875
                },
                {
                    "pressure": 1.0,
                    "x": 2086.504150390625,
                    "y": 628.9430541992188
                },
                {
                    "pressure": 1.0,
                    "x": 2086.504150390625,
                    "y": 615.9349365234375
                },
                {
                    "pressure": 1.0,
                    "x": 2090.840087890625,
                    "y": 602.9268188476563
                },
                {
                    "pressure": 1.0,
                    "x": 2090.840087890625,
                    "y": 594.2546997070313
                },
                {
                    "pressure": 1.0,
                    "x": 2095.17626953125,
                    "y": 576.9105224609375
                },
                {
                    "pressure": 1.0,
                    "x": 2099.51220703125,
                    "y": 563.9024047851563
                },
                {
                    "pressure": 1.0,
                    "x": 2099.51220703125,
                    "y": 555.2303466796875
                },
                {
                    "pressure": 1.0,
                    "x": 2099.51220703125,
                    "y": 546.5582275390625
                },
                {
                    "pressure": 1.0,
                    "x": 2099.51220703125,
                    "y": 533.5501098632813
                },
                {
                    "pressure": 1.0,
                    "x": 2099.51220703125,
                    "y": 520.5419921875
                },
                {
                    "pressure": 1.0,
                    "x": 2095.17626953125,
                    "y": 507.5338439941406
                },
                {
                    "pressure": 1.0,
                    "x": 2090.840087890625,
                    "y": 494.5257263183594
                },
                {
                    "pressure": 1.0,
                    "x": 2086.504150390625,
                    "y": 481.517578125
                },
                {
                    "pressure": 1.0,
                    "x": 2077.83203125,
                    "y": 472.8454895019531
                },
                {
                    "pressure": 1.0,
                    "x": 2069.159912109375,
                    "y": 464.17340087890625
                },
                {
                    "pressure": 1.0,
                    "x": 2060.48779296875,
                    "y": 451.165283203125
                },
                {
                    "pressure": 1.0,
                    "x": 2047.479736328125,
                    "y": 442.4931945800781
                },
                {
                    "pressure": 1.0,
                    "x": 2034.4715576171875,
                    "y": 433.82110595703125
                },
                {
                    "pressure": 1.0,
                    "x": 2021.46337890625,
                    "y": 425.1490173339844
                },
                {
                    "pressure": 1.0,
                    "x": 2004.1192626953125,
                    "y": 412.1408996582031
                },
                {
                    "pressure": 1.0,
                    "x": 1986.775146484375,
                    "y": 403.46881103515625
                },
                {
                    "pressure": 1.0,
                    "x": 1965.0948486328125,
                    "y": 399.13275146484375
                },
                {
                    "pressure": 1.0,
                    "x": 1952.0867919921875,
                    "y": 390.4606628417969
                },
                {
                    "pressure": 1.0,
                    "x": 1934.7425537109375,
                    "y": 386.1246337890625
                },
                {
                    "pressure": 1.0,
                    "x": 1913.0623779296875,
                    "y": 381.78857421875
                },
                {
                    "pressure": 1.0,
                    "x": 1895.7181396484375,
                    "y": 373.1164855957031
                },
                {
                    "pressure": 1.0,
                    "x": 1869.701904296875,
                    "y": 368.78045654296875
                },
                {
                    "pressure": 1.0,
                    "x": 1852.3577880859375,
                    "y": 364.44439697265625
                },
                {
                    "pressure": 1.0,
                    "x": 1826.3414306640625,
                    "y": 360.1083679199219
                },
                {
                    "pressure": 1.0,
                    "x": 1795.9891357421875,
                    "y": 351.436279296875
                },
                {
                    "pressure": 1.0,
                    "x": 1765.6368408203125,
                    "y": 347.1002502441406
                },
                {
                    "pressure": 1.0,
                    "x": 1735.2845458984375,
                    "y": 347.1002502441406
                },
                {
                    "pressure": 1.0,
                    "x": 1709.268310546875,
                    "y": 347.1002502441406
                },
                {
                    "pressure": 1.0,
                    "x": 1683.2520751953125,
                    "y": 347.1002502441406
                },
                {
                    "pressure": 1.0,
                    "x": 1670.243896484375,
                    "y": 347.1002502441406
                },
                {
                    "pressure": 1.0,
                    "x": 1652.8997802734375,
                    "y": 351.436279296875
                },
                {
                    "pressure": 1.0,
                    "x": 1631.219482421875,
                    "y": 360.1083679199219
                },
                {
                    "pressure": 1.0,
                    "x": 1626.8834228515625,
                    "y": 368.78045654296875
                },
                {
                    "pressure": 1.0,
                    "x": 1618.21142578125,
                    "y": 373.1164855957031
                },
                {
                    "pressure": 1.0,
                    "x": 1618.21142578125,
                    "y": 377.4525451660156
                },
                {
                    "pressure": 1.0,
                    "x": 1609.539306640625,
                    "y": 390.4606628417969
                },
                {
                    "pressure": 1.0,
                    "x": 1605.2032470703125,
                    "y": 399.13275146484375
                },
                {
                    "pressure": 1.0,
                    "x": 1600.8671875,
                    "y": 407.8048400878906
                },
                {
                    "pressure": 1.0,
                    "x": 1592.195068359375,
                    "y": 416.4769287109375
                },
                {
                    "pressure": 1.0,
                    "x": 1579.18701171875,
                    "y": 433.82110595703125
                },
                {
                    "pressure": 1.0,
                    "x": 1570.514892578125,
                    "y": 438.1571350097656
                },
                {
                    "pressure": 1.0,
                    "x": 1561.8427734375,
                    "y": 455.5013122558594
                },
                {
                    "pressure": 1.0,
                    "x": 1548.834716796875,
                    "y": 464.17340087890625
                },
                {
                    "pressure": 1.0,
                    "x": 1535.8265380859375,
                    "y": 481.517578125
                },
                {
                    "pressure": 1.0,
                    "x": 1527.1544189453125,
                    "y": 490.1896667480469
                },
                {
                    "pressure": 1.0,
                    "x": 1509.810302734375,
                    "y": 507.5338439941406
                },
                {
                    "pressure": 1.0,
                    "x": 1505.4742431640625,
                    "y": 516.2059326171875
                },
                {
                    "pressure": 1.0,
                    "x": 1496.8021240234375,
                    "y": 529.2140502929688
                },
                {
                    "pressure": 1.0,
                    "x": 1492.466064453125,
                    "y": 537.8861694335938
                },
                {
                    "pressure": 1.0,
                    "x": 1492.466064453125,
                    "y": 546.5582275390625
                }
            ],
            "radiusPx": 4.0
        },
        {
            "color": [
                0.7087889909744263,
                0.9034749269485474,
                0.04883650690317154,
                1.0
            ],
            "points": [
                {
                    "pressure": 1.0,
                    "x": 1717.9404296875,
                    "y": 741.68017578125
                },
                {
                    "pressure": 1.0,
                    "x": 1717.9404296875,
                    "y": 746.0162353515625
                },
                {
                    "pressure": 1.0,
                    "x": 1717.9404296875,
                    "y": 759.0243530273438
                },
                {
                    "pressure": 1.0,
                    "x": 1717.9404296875,
                    "y": 767.6964721679688
                },
                {
                    "pressure": 1.0,
                    "x": 1713.6043701171875,
                    "y": 789.376708984375
                },
                {
                    "pressure": 1.0,
                    "x": 1709.268310546875,
                    "y": 793.7127075195313
                },
                {
                    "pressure": 1.0,
                    "x": 1704.9322509765625,
                    "y": 819.72900390625
                },
                {
                    "pressure": 1.0,
                    "x": 1704.9322509765625,
                    "y": 824.0650024414063
                },
                {
                    "pressure": 1.0,
                    "x": 1704.9322509765625,
                    "y": 837.0731811523438
                },
                {
                    "pressure": 1.0,
                    "x": 1704.9322509765625,
                    "y": 841.4091796875
                },
                {
                    "pressure": 1.0,
                    "x": 1704.9322509765625,
                    "y": 845.7452392578125
                },
                {
                    "pressure": 1.0,
                    "x": 1717.9404296875,
                    "y": 845.7452392578125
                },
                {
                    "pressure": 1.0,
                    "x": 1730.948486328125,
                    "y": 845.7452392578125
                },
                {
                    "pressure": 1.0,
                    "x": 1739.62060546875,
                    "y": 845.7452392578125
                },
                {
                    "pressure": 1.0,
                    "x": 1765.6368408203125,
                    "y": 841.4091796875
                },
                {
                    "pressure": 1.0,
                    "x": 1774.3089599609375,
                    "y": 832.7371215820313
                },
                {
                    "pressure": 1.0,
                    "x": 1791.653076171875,
                    "y": 819.72900390625
                },
                {
                    "pressure": 1.0,
                    "x": 1795.9891357421875,
                    "y": 811.056884765625
                },
                {
                    "pressure": 1.0,
                    "x": 1795.9891357421875,
                    "y": 785.0406494140625
                },
                {
                    "pressure": 1.0,
                    "x": 1795.9891357421875,
                    "y": 772.0325317382813
                },
                {
                    "pressure": 1.0,
                    "x": 1795.9891357421875,
                    "y": 763.3604125976563
                },
                {
                    "pressure": 1.0,
                    "x": 1791.653076171875,
                    "y": 733.0081176757813
                },
                {
                    "pressure": 1.0,
                    "x": 1787.317138671875,
                    "y": 724.3359985351563
                },
                {
                    "pressure": 1.0,
                    "x": 1761.30078125,
                    "y": 698.3197631835938
                },
                {
                    "pressure": 1.0,
                    "x": 1752.6287841796875,
                    "y": 693.9837036132813
                },
                {
                    "pressure": 1.0,
                    "x": 1739.62060546875,
                    "y": 685.3116455078125
                },
                {
                    "pressure": 1.0,
                    "x": 1696.2601318359375,
                    "y": 672.3035278320313
                },
                {
                    "pressure": 1.0,
                    "x": 1683.2520751953125,
                    "y": 667.9674682617188
                },
                {
                    "pressure": 1.0,
                    "x": 1648.563720703125,
                    "y": 667.9674682617188
                },
                {
                    "pressure": 1.0,
                    "x": 1644.2276611328125,
                    "y": 667.9674682617188
                },
                {
                    "pressure": 1.0,
                    "x": 1635.5555419921875,
                    "y": 667.9674682617188
                },
                {
                    "pressure": 1.0,
                    "x": 1626.8834228515625,
                    "y": 667.9674682617188
                },
                {
                    "pressure": 1.0,
                    "x": 1622.5474853515625,
                    "y": 667.9674682617188
                },
                {
                    "pressure": 1.0,
                    "x": 1618.21142578125,
                    "y": 672.3035278320313
                },
                {
                    "pressure": 1.0,
                    "x": 1618.21142578125,
                    "y": 676.6395263671875
                },
                {
                    "pressure": 1.0,
                    "x": 1618.21142578125,
                    "y": 680.9755859375
                },
                {
                    "pressure": 1.0,
                    "x": 1622.5474853515625,
                    "y": 685.3116455078125
                },
                {
                    "pressure": 1.0,
                    "x": 1631.219482421875,
                    "y": 685.3116455078125
                }
            ],
            "radiusPx": 4.0
        },
        {
            "color": [
                0.7087889909744263,
                0.9034749269485474,
                0.04883650690317154,
                1.0
            ],
            "points": [
                {
                    "pressure": 1.0,
                    "x": 1696.2601318359375,
                    "y": 1288.021728515625
                },
                {
                    "pressure": 1.0,
                    "x": 1691.924072265625,
                    "y": 1288.021728515625
                },
                {
                    "pressure": 1.0,
                    "x": 1683.2520751953125,
                    "y": 1288.021728515625
                },
                {
                    "pressure": 1.0,
                    "x": 1678.916015625,
                    "y": 1288.021728515625
                },
                {
                    "pressure": 1.0,
                    "x": 1648.563720703125,
                    "y": 1288.021728515625
                },
                {
                    "pressure": 1.0,
                    "x": 1635.5555419921875,
                    "y": 1288.021728515625
                },
                {
                    "pressure": 1.0,
                    "x": 1613.8753662109375,
                    "y": 1288.021728515625
                },
                {
                    "pressure": 1.0,
                    "x": 1574.8509521484375,
                    "y": 1288.021728515625
                },
                {
                    "pressure": 1.0,
                    "x": 1544.4986572265625,
                    "y": 1288.021728515625
                },
                {
                    "pressure": 1.0,
                    "x": 1492.466064453125,
                    "y": 1292.3577880859375
                },
                {
                    "pressure": 1.0,
                    "x": 1449.105712890625,
                    "y": 1296.6937255859375
                },
                {
                    "pressure": 1.0,
                    "x": 1405.7452392578125,
                    "y": 1301.02978515625
                },
                {
                    "pressure": 1.0,
                    "x": 1392.737060546875,
                    "y": 1301.02978515625
                },
                {
                    "pressure": 1.0,
                    "x": 1366.7208251953125,
                    "y": 1305.3658447265625
                },
                {
                    "pressure": 1.0,
                    "x": 1349.376708984375,
                    "y": 1305.3658447265625
                },
                {
                    "pressure": 1.0,
                    "x": 1340.70458984375,
                    "y": 1305.3658447265625
                },
                {
                    "pressure": 1.0,
                    "x": 1336.3685302734375,
                    "y": 1305.3658447265625
                }
            ],
            "radiusPx": 4.0
        }
    ],
    "visible": true
}
